fenicsx_plotly/__init__.py
fenicsx_plotly/_fenicsx_plotly.py
fenicsx_plotly-0.3.0.dist-info/LICENSE
fenicsx_plotly-0.3.0.dist-info/METADATA
fenicsx_plotly-0.3.0.dist-info/WHEEL
fenicsx_plotly-0.3.0.dist-info/top_level.txt
fenicsx_plotly-0.3.0.dist-info/RECORD
