Metadata-Version: 2.1
Name: fenicsx-plotly
Version: 0.3.0
Summary: Lightweight library for plotting FEniCS x objects using plotly
Author-email: Henrik Finsberg <henriknf@simula.no>
License: Copyright 2022 Henrik Finsberg
License-File: LICENSE
Requires-Dist: fenics-dolfinx
Requires-Dist: numpy
Requires-Dist: plotly
Requires-Dist: ipywidgets (==7.7.2)
Provides-Extra: all
Requires-Dist: fenicsx-plotly[test] ; extra == 'all'
Requires-Dist: fenicsx-plotly[dev] ; extra == 'all'
Requires-Dist: fenicsx-plotly[docs] ; extra == 'all'
Provides-Extra: dev
Requires-Dist: pdbpp ; extra == 'dev'
Requires-Dist: ipython ; extra == 'dev'
Requires-Dist: bump2version ; extra == 'dev'
Requires-Dist: pre-commit ; extra == 'dev'
Provides-Extra: docs
Requires-Dist: jupyter-book ; extra == 'docs'
Requires-Dist: jupytext ; extra == 'docs'
Requires-Dist: ipython (<8.7.0) ; extra == 'docs'
Provides-Extra: test
Requires-Dist: pytest ; extra == 'test'
Requires-Dist: pytest-cov ; extra == 'test'
